{"cameraMode":{"drawMode":0,"name":"Shaded","section":"Shading Mode"},"sceneLighting":true,"audioPlay":false,"sceneViewState":{"m_AlwaysRefresh":false,"showFog":true,"showSkybox":true,"showFlares":true,"showImageEffects":true,"showParticleSystems":true,"showVisualEffectGraphs":true,"m_FxEnabled":true},"in2DMode":false,"pivot":{"x":731.5975952148438,"y":642.3915405273438,"z":114.454345703125},"rotation":{"x":-0.034783054143190387,"y":0.03867213428020477,"z":-0.0013236971572041512,"w":-0.998747706413269},"size":685.3431396484375,"orthographic":false}